alice_images/__init__.py
alice_images/alice_images_api.py
alice_images/cli.py
alice_images-0.1.0.dist-info/LICENSE
alice_images-0.1.0.dist-info/METADATA
alice_images-0.1.0.dist-info/WHEEL
alice_images-0.1.0.dist-info/entry_points.txt
alice_images-0.1.0.dist-info/top_level.txt
alice_images-0.1.0.dist-info/RECORD
